lib/__init__.py
lib/crc.py
shacrc-0.0.1.dist-info/METADATA
shacrc-0.0.1.dist-info/WHEEL
shacrc-0.0.1.dist-info/top_level.txt
shacrc-0.0.1.dist-info/RECORD
