Metadata-Version: 2.1
Name: shacrc
Version: 0.0.1
Summary: None of your business
Home-page: UNKNOWN
Author: Anonymous
Author-email: 
License: UNKNOWN
Keywords: crc
Platform: UNKNOWN
Classifier: Development Status :: 1 - Planning
Classifier: Intended Audience :: Developers
Classifier: Programming Language :: Python :: 3
Classifier: Operating System :: Unix
Classifier: Operating System :: MacOS :: MacOS X
Classifier: Operating System :: Microsoft :: Windows
